Metadata-Version: 2.1
Name: simloc
Version: 0.0.1
Summary: Simple localization
Author-email: Chersky <lega4e@lega4e.ru>
Maintainer-email: Chersky <lega4e@lega4e.ru>
License: MIT License
Project-URL: Repository, https://github.com/lega4e/simloc.git
Keywords: lega4e,localization,simple
Requires-Python: >=3.9
License-File: LICENSE
